tests/__init__.py
tests/test_core.py
tests/test_web.py
wiki/__init__.py
wiki/cli.py
wiki/core.py
wiki/web/__init__.py
wiki/web/forms.py
wiki/web/routes.py
wiki/web/user.py
wiki/web/static/bootstrap.css
wiki/web/static/bootstrap.min.js
wiki/web/static/jquery.min.js
wiki/web/static/pygments.css
wiki/web/static/responsive.css
wiki/web/templates/404.html
wiki/web/templates/base.html
wiki/web/templates/create.html
wiki/web/templates/editor.html
wiki/web/templates/helpers.html
wiki/web/templates/home.html
wiki/web/templates/index.html
wiki/web/templates/login.html
wiki/web/templates/move.html
wiki/web/templates/page.html
wiki/web/templates/search.html
wiki/web/templates/tag.html
wiki/web/templates/tags.html
wiki2-3.0.2.dist-info/LICENSE
wiki2-3.0.2.dist-info/METADATA
wiki2-3.0.2.dist-info/WHEEL
wiki2-3.0.2.dist-info/entry_points.txt
wiki2-3.0.2.dist-info/top_level.txt
wiki2-3.0.2.dist-info/RECORD
