Metadata-Version: 2.1
Name: wiki2
Version: 3.0.2
Summary: simple python markdown wiki with web ui
Home-page: https://github.com/alexanderjulo/wiki
Author: Alexander Jung-Loddenkemper
Author-email: alexander@julo.ch
License: UNKNOWN
Platform: UNKNOWN
Requires-Python: >3.7
Requires-Dist: Flask (>=0.9)
Requires-Dist: Click (<7,>=6)
Requires-Dist: Flask-Login (>=0.4)
Requires-Dist: Flask-WTF (>=0.8)
Requires-Dist: Markdown (>=2.2.0)
Requires-Dist: Pygments (>=1.5)
Requires-Dist: WTForms (>=1.0.2)
Requires-Dist: Werkzeug (>=0.8.3)
